Metadata-Version: 2.1
Name: tanvircalculator
Version: 1.1.1
Summary: A simple calculator package
Home-page: https://github.com/Tanvir-yzu/simplecalculator.git
Author: Tanvir-yzu
Author-email: 2020tanvir1971@gmail.com
Classifier: Programming Language :: Python :: 3
Classifier: License :: OSI Approved :: MIT License
Classifier: Operating System :: OS Independent
License-File: LICENCE.txt
